<poster>MetalKettle</poster>
<fanart>https://raw.githubusercontent.com/metalkettle/MetalKettles-Addon-Repository/master/fanart.jpg</fanart>
<item>
<title>Johnny English Reborn (2011)</title>
<link>http://redirector.googlevideo.com/videoplayback?id=b5f59c90aeee661b&itag=22&source=picasa&cmo=sensitive_content%3Dyes&ip=0.0.0.0&ipbits=0&expire=1404138418&sparams=id,itag,source,ip,ipbits,expire&signature=38F0879FC70180CF9D66788C291138CB9205316F.8032950E23A847D70EC8C5CFAF87A663EAB60CB5&key=lh1</link>
<thumbnail>https://lh5.googleusercontent.com/-7dvG1gEgDt4/U4c5iamUC1I/AAAAAAAAExw/p36piEyCMmA/Johnny.English.Reborn.2011.720p.BrRip.x264.jpg</thumbnail>
</item>

<item>
<title>Johnny English (2003)</title>
<link>http://redirector.googlevideo.com/videoplayback?id=669962ff5209cb6a&itag=22&source=picasa&cmo=sensitive_content%3Dyes&ip=0.0.0.0&ipbits=0&expire=1404138417&sparams=id,itag,source,ip,ipbits,expire&signature=54BD38392029C8B8F81AB65AA447C1F81309ED81.D5E206B6F8FB9BC506FDEE69FB25DDD7BA6ADE50&key=lh1</link>
<thumbnail>https://lh3.googleusercontent.com/-UbWVFSileug/U4c5iGDvXdI/AAAAAAAAExk/Nbfpj_tn46k/Johnny.English.2003.720p.BrRip.264.YIFY.jpg</thumbnail>
</item>